{"title":"NY Times, Tue, Jan 14, 2020","author":"Jim Peredo","editor":"Will Shortz","copyright":"2020, The New York Times","publisher":"The New York Times","date":"1/14/2020","notepad":null,"jnotes":null,"shadecircles":null,"interpretcolors":null,"key":null,"hold":null,"track":null,"autowrap":null,"mini":null,"id":null,"id2":null,"code":null,"dow":"Tuesday","type":null,"target":"/Crossword?date=1/14/2020","valid":true,"uniclue":false,"admin":false,"hastitle":false,"navigate":true,"auto":false,"size":{"rows":15,"cols":15},"grid":["A","N","N","E",".","T","R","E","E","S",".","A","C","E","D","P","E","O","N",".","R","U","R","A","L",".","C","A","N","E","P","U","T","T",".","A","N","G","R","Y","B","I","R","D","S",".","T","A","O",".","S","N","O","T",".","A","D","A","G","E","G","R","O","U","C","H","Y",".","H","A","N",".","M","A","R","M","A","N","R","A","Y",".","I","D","L","E",".","E","M","T","C","L","E","A","R",".",".","M","A","E",".","A","L","E","S",".",".",".","G","R","U","M","P","Y","C","A","T",".",".",".","C","O","D","E",".","H","A","L",".",".","W","A","S","T","E","A","V","E",".","R","O","S","Y",".","S","E","N","I","O","R","B","U","M",".","A","H","H",".","L","A","D","Y","B","U","G","A","L","I","B","I",".","A","H","A","B",".","R","E","C",".","R","A","G","I","N","G","B","U","L","L",".","A","R","A","B","E","T","O","N",".","A","L","G","A","E",".","T","I","N","A","T","E","D","S",".","M","E","O","W","S",".","E","A","S","Y"],"gridnums":[1,2,3,4,0,5,6,7,8,9,0,10,11,12,13,14,0,0,0,0,15,0,0,0,0,0,16,0,0,0,17,0,0,0,0,18,0,0,0,0,19,0,0,0,0,0,20,0,0,0,21,0,0,0,0,22,0,0,0,0,23,0,0,0,24,0,0,0,25,26,0,0,27,0,0,28,0,0,0,0,0,0,29,0,0,0,0,30,0,0,31,0,0,0,0,0,0,32,0,0,0,33,0,0,0,0,0,0,34,0,35,36,0,0,0,37,0,0,0,0,38,39,40,0,0,41,0,0,0,0,42,0,43,44,45,46,0,0,0,47,0,0,0,0,48,0,0,0,0,0,49,0,0,0,50,0,0,0,51,0,0,0,0,0,0,52,0,0,53,0,0,54,55,0,0,0,56,0,0,0,57,0,0,0,0,58,0,0,0,0,0,59,0,0,60,61,0,0,0,0,62,0,0,0,0,0,63,0,0,0,64,0,0,0,0,65,0,0,0,0,0,66,0,0,0],"circles":null,"acrossmap":null,"downmap":null,"rbars":null,"bbars":null,"clues":{"across":["1. Actress Hathaway","5. Forest components","10. Scored 100 on","14. Hacienda drudge","15. Like much of the Dakotas","16. Alternative to a walker","17. When doubled, miniature golf","18. Video game franchise in which the enemies are pigs","20. &quot;The ___ of Pooh&quot; (Benjamin Hoff book)","21. Rotten little twerp","22. &quot;Time is money,&quot; e.g.","23. With 51-Across, Eric Carle kid-lit book, after &quot;The&quot;","25. Pal of Chewbacca","27. Put a ding in, say","28. Dadaism pioneer","29. Just sitting around","30. 911 responder, in brief","31. Perfectly understood","32. ___ Jemison, first black woman in space","33. Pub pints","34. Feline in an internet meme","38. A wartime communication might be sent in it","41. Rogue computer in &quot;2001&quot;","42. Outcome of haste, it&#39;s said","46. &quot;Hail!,&quot; to Caesar","47. Promising, as a future","48. Soon-to-be graduate, usually","49. Backside, in Britain","50. &quot;That&#39;s the spot!&quot;","51. See 23-Across","52. Story that one generally sticks to, whether it&#39;s true or not","54. Pursuer of an &quot;accursed white whale&quot;","56. Button on a cam","57. 1980 boxing biopic","59. Many a Meccan","61. Princely school","62. Aquarium buildup","63. Fey of &quot;30 Rock&quot;","64. &quot;Bill &amp; ___ Excellent Adventure&quot;","65. Requests for Friskies, perhaps","66. &quot;No problemo!&quot;"],"down":["1. 18-Across, e.g.","2. Like hosiery hues, typically","3. Zero, zip, nada","4. Rapper&#39;s posse","5. In poor taste","6. Like undercooked eggs","7. Logician&#39;s &quot;therefore&quot;","8. April event that&#39;s &quot;green&quot;","9. Sneakily clever","10. Gastric juice, e.g.","11. Apple coating at a fair","12. When checkmate is most likely to occur","13. &quot;Just&quot; punishment","19. Cause of ruination","23. Yukon S.U.V. maker","24. Vikki who sang &quot;It Must Be Him&quot;","26. Smart ___","29. Subtly suggest","33. &quot;Be that as it may ...&quot;","35. &quot;Here&#39;s trouble!&quot;","36. BuzzFeed competitor","37. Totally blown away","38. Musical for which Liza Minnelli won an Oscar","39. Release a fertilizable egg","40. Part man, part deity","43. Stereotypical place of exile","44. Sam the Froot Loops mascot and others","45. Tiny bit of energy","47. Drops from the sky","48. Relatives of weasels with dark fur","51. Legal drama with Susan Dey","53. Coal containers","55. ___ Boss (German fashion house)","58. Leg, in old slang","60. San Francisco area, with &quot;the&quot;"]},"answers":{"across":["ANNE","TREES","ACED","PEON","RURAL","CANE","PUTT","ANGRYBIRDS","TAO","SNOT","ADAGE","GROUCHY","HAN","MAR","MANRAY","IDLE","EMT","CLEAR","MAE","ALES","GRUMPYCAT","CODE","HAL","WASTE","AVE","ROSY","SENIOR","BUM","AHH","LADYBUG","ALIBI","AHAB","REC","RAGINGBULL","ARAB","ETON","ALGAE","TINA","TEDS","MEOWS","EASY"],"down":["APP","NEUTRAL","NOTAONE","ENTOURAGE","TRASHY","RUNNY","ERGO","EARTHDAY","SLY","ACID","CARAMEL","ENDGAME","DESERTS","BANE","GMC","CARR","ALEC","IMPLY","ATANYRATE","UHOH","MASHABLE","AWED","CABARET","OVULATE","DEMIGOD","SIBERIA","TOUCANS","ERG","RAIN","SABLES","LALAW","BINS","HUGO","GAM","BAY"]}}