{"title":"WIDE-OPEN SPACES","author":"Byron Walden","editor":"Will Shortz","copyright":"2020, The New York Times","publisher":"The New York Times","date":"5/17/2020","notepad":null,"jnotes":null,"shadecircles":null,"interpretcolors":null,"key":null,"hold":null,"track":null,"autowrap":null,"mini":null,"id":null,"id2":null,"code":null,"dow":"Sunday","type":null,"target":"/Crossword?date=5/17/2020","valid":true,"uniclue":false,"admin":false,"hastitle":true,"navigate":true,"auto":false,"size":{"rows":21,"cols":21},"grid":["A","T","P","A","R",".",".","A","N","C","H","O","V","Y",".","S","P","E","E","D","O","R","H","I","N","O",".","A","P","A","R","I","C","I","O",".","P","L","A","N","E","R","K","E","N","T","C","I","G","A","R","E","T","T","E","S",".","L","A","S","T","E","D","A","V","E","S",".","S","E","R","R","A","T","E","D",".","F","U","N","T","I","M","E","N","A","T",".","W","E","N","T","A","T","I","T",".","B","A","R","T","E","R","E","R","S","U","R","E","B","E","T",".","T","I","N",".","C","O","N","G","O","R","E","D","S","A","L","E","X","A",".",".","K","I","N","G","H","U","S","S","E","I","N",".",".",".","S","T","E","T",".","S","T","O","V","E","T","O","P","S",".","S","L","A","T","E","D",".",".",".","R","E","C","I","P","E",".","H","O","P","E","S",".","S","U","A","V","E",".","S","E","A","S","O","N","S",".","D","E","T","E","S","T","S",".","S","H","I","N","O","U","R","L","O","R","D",".","S","A","P","I","D",".","P","I","S","T","O","L","S","U","S","N","A",".","N","E","B","U","L","A","E",".","N","A","T","U","R","E","S",".","T","H","I","R","D",".","R","E","S","I","N",".","I","G","U","A","N","A",".",".",".","S","I","E","G","E","L",".","U","S","A","I","N","B","O","L","T",".","L","I","Z","A",".",".",".","E","C","U","R","R","E","N","C","I","E","S",".",".","B","I","D","E","N","Z","E","P","P","O","M","A","R","X",".","B","E","T",".","B","E","L","A","I","R","S","A","Q","U","I","L","I","N","E",".","C","U","L","T","H","E","R","O",".","T","O","W","M","U","Z","Z","L","E","D",".","H","O","T","S","E","A","T","S",".","M","A","Z","E","F","I","Z","Z","E","R",".","H","U","N","T","E","R","G","A","T","H","E","R","E","R","I","N","L","A","T","E",".","A","R","G","O","N","G","A","S",".","S","N","O","R","E","R","E","E","S","E","S",".","P","L","A","N","S","O","N",".",".","T","U","D","O","R"],"gridnums":[1,2,3,4,5,0,0,6,7,8,9,10,11,12,0,13,14,15,16,17,18,19,0,0,0,0,0,20,0,0,0,0,0,0,0,0,21,0,0,0,0,0,22,0,0,0,0,23,0,0,0,0,0,0,0,0,0,24,0,0,0,0,0,25,0,0,0,0,26,0,0,0,0,0,0,0,0,27,0,0,0,0,0,0,28,0,0,0,29,0,0,0,0,0,0,0,0,30,0,0,0,0,0,0,0,31,0,0,32,0,0,0,0,33,0,0,0,34,0,0,0,0,0,0,0,0,35,0,0,0,0,0,0,36,0,0,0,37,0,0,0,0,0,0,0,0,0,38,0,0,0,0,39,40,0,0,0,0,0,0,0,0,41,0,0,42,43,44,0,0,0,45,46,0,0,0,0,0,47,0,0,0,48,0,49,0,0,0,0,0,50,51,0,0,0,0,0,0,52,0,0,0,0,0,53,0,54,0,0,0,55,0,0,0,0,0,0,0,56,0,0,0,0,0,57,0,58,0,0,0,0,59,0,0,0,0,60,0,61,0,0,0,0,0,62,0,0,0,0,0,0,0,63,0,0,0,64,0,65,0,0,0,0,0,66,0,0,0,0,0,0,0,0,67,0,0,0,0,68,0,69,0,0,0,70,0,0,0,0,0,71,72,73,74,0,0,0,75,0,0,76,0,0,0,0,0,0,0,0,0,77,0,0,0,0,78,79,80,0,0,0,0,0,0,0,81,0,0,0,82,83,0,0,0,0,0,84,0,0,0,0,0,0,0,0,85,0,0,0,86,0,0,0,0,87,0,0,88,0,0,0,0,0,0,0,89,0,0,0,0,0,0,0,0,90,0,0,0,91,0,0,0,0,0,0,92,0,0,0,0,0,0,0,0,93,0,0,0,0,94,0,0,0,0,0,0,95,0,0,0,0,0,0,0,0,96,0,0,0,0,97,0,0,0,0,0,0,98,0,0,0,0,0,0,0,0,99,0,0,0,0],"circles":null,"acrossmap":null,"downmap":null,"rbars":null,"bbars":null,"clues":{"across":["1. How some stock shares are sold","6. Caesar salad ingredient","13. Big name in swimwear","19. African grazer","20. Yalitza ___, Best Actress nominee for 2018&#39;s &quot;Roma&quot;","21. Woodworking machine","22. R. J. Reynolds product that once sponsored &quot;The Dick Van Dyke Show&quot;","24. Had legs, so to speak","25. Flying class?","26. Like some leaves and knives","27. Blast","28. &quot;The Confessions of ___ Turner&quot; (1967 Pulitzer-winning novel)","29. Scrapped","30. One who might say &quot;Your money&#39;s no good here&quot;?","31. Overwhelming favorite","33. Roofing material","34. Dyes that can be used as pH indicators","35. Echo voice","36. Eponym of Aqaba&#39;s airport","38. Editorial reversal","39. Simmering sites","41. On the schedule","45. Chef&#39;s creation","47. Crosses one&#39;s fingers","49. Sophisticated","50. Subjects of four famous violin concertos by Vivaldi","52. Can&#39;t take","54. Body part that&#39;s also a Hebrew letter","55. Christ, to Christians","56. Flavorful","57. Colts, maybe","59. Sch. on Chesapeake Bay","60. Interstellar clouds","62. Fundamental dispositions","63. With 55-Down, inning enders","65. Pourable art material","66. Creature seen basking on the shores of the Galápagos","67. Superman co-creator Jerry","69. Sports icon with the autobiography &quot;Faster Than Lightning&quot;","71. Entertainer Minnelli","75. Bitcoin and the like","77. 47th U.S. vice president","78. Comic actor whose wife left him to marry their neighbor, Frank Sinatra","81. Airer of the gospel music reality competition &quot;Sunday Best&quot;","82. Classic Chevrolets","84. Eaglelike","85. One with a small but devoted fan base","87. AAA service","88. Restrained from biting","89. Places of intense scrutiny","90. Entertainment on a diner place mat, maybe","91. Alka-Seltzer tablet, for one","92. Early omnivore","94. Returning after curfew, say","95. Substance used to preserve the Declaration of Independence","96. Apt rhyme for &quot;bore&quot;","97. ___ Pieces","98. Has in mind","99. Mary I or Elizabeth I"],"down":["1. Major tributary of the Mississippi","2. Gymnastics event for both men and women","3. The ___ State, nickname for Maine","4. Targets of formicide","5. Mythical flier","6. Isolated","7. Account","8. Popular performance-enhancing supplement for athletes","9. Freaking out","10. Good-sized wedding band","11. Competed","12. Rockyesque interjections","13. Spends extravagantly","14. Some biodiesel sources","15. Victorian home?","16. Whole","17. Judged","18. Things taken while waiting","20. Representative","23. &quot;Capeesh&quot;","27. Whiffs","29. Org. for lightweights","30. End-of-level challenges in video games","32. Items in 18&quot; x 18&quot; x 1 3/4&quot; boxes","34. Like the hands in the Allstate logo","36. Keystone ___","37. ___ &amp; the Blowfish","39. What sneers express","40. Popular dating app","42. Lake drained by the Truckee River","43. Iniquities","44. Places of iniquity","46. Spanish &quot;that&quot;","48. State capital on the Mississippi","50. Word with roll or bar","51. Muppet wearing a horizontally striped shirt","52. Chinese port city on Korea Bay","53. Occupy, as a booth","55. See 63-Across","56. English county that&#39;s home to Brighton","58. Weather map symbol","61. Butter, in Burgundy","62. Doctors Without Borders and others, in brief","64. Having a low neckline, as a dress","66. &quot;Gotta split&quot;","68. Group of 18th-century thinkers that included Voltaire and Rousseau","70. Numbers of concern to showrunners","72. The &quot;Last Great Race on Earth&quot;","73. Love match?","74. Respondent","76. South African money","77. Slo-___ fuse","78. Pan flute musician in iconic commercials of the 1980s","79. Like a jackass","80. Your current occupation?","82. Some skilled workers in &quot;Brave New World&quot;","83. Lead-in to while","85. Party line?","86. Former North Carolina senator Kay ___","89. Let fly","90. Clickable list","92. W.W. II general ___ Arnold","93. Clock setting on the Big Island: Abbr."]},"answers":{"across":["ATPAR","ANCHOVY","SPEEDO","RHINO","APARICIO","PLANER","KENTCIGARETTES","LASTED","AVES","SERRATED","FUNTIME","NAT","WENTATIT","BARTERER","SUREBET","TIN","CONGOREDS","ALEXA","KINGHUSSEIN","STET","STOVETOPS","SLATED","RECIPE","HOPES","SUAVE","SEASONS","DETESTS","SHIN","OURLORD","SAPID","PISTOLS","USNA","NEBULAE","NATURES","THIRD","RESIN","IGUANA","SIEGEL","USAINBOLT","LIZA","ECURRENCIES","BIDEN","ZEPPOMARX","BET","BELAIRS","AQUILINE","CULTHERO","TOW","MUZZLED","HOTSEATS","MAZE","FIZZER","HUNTERGATHERER","INLATE","ARGONGAS","SNORE","REESES","PLANSON","TUDOR"],"down":["ARKANSAS","THEVAULT","PINETREE","ANTS","ROC","APART","NARRATIVE","CREATINE","HITTINGTHEPANICBUTTON","OCTET","VIED","YOS","SPLURGES","PLANTOILS","EASTERNAUSTRALIA","ENTIRE","DEEMED","ORDERS","AGENT","ISEE","FANS","WBA","BOSSES","EXTRALARGEPIZZAS","CUPPED","KOPS","HOOTIE","SCORN","TINDER","TAHOE","EVILS","DENS","ESO","STPAUL","SUSHI","ERNIE","DALIAN","SITAT","OUTS","SUSSEX","SUN","BEURRE","NGOS","DECOLLETE","IBETTERGO","LUMIERES","NIELSENS","IDITAROD","ZEROZERO","ANSWERER","RAND","BLO","ZAMFIR","EQUINE","PUZZLE","BETAS","ERST","CONGA","HAGAN","HURL","MENU","HAP","HST"]}}