{"title":"New York Times, Monday, August 1, 2022","author":"Garrett Chalfin","editor":"Will Shortz","copyright":"2022, The New York Times","publisher":"The New York Times","date":"8/1/2022","notepad":null,"jnotes":"<p>17-year-old Garrett Chalfin is the latest addition to our <a href=\"https://www.xwordinfo.com/Youngest\">Teenage Constructors</a> page. He slots in at #28.</p>","shadecircles":null,"interpretcolors":null,"key":null,"hold":null,"track":null,"autowrap":null,"mini":null,"id":null,"id2":null,"code":null,"dow":"Monday","type":null,"target":"/Crossword?date=8/1/2022","valid":true,"uniclue":false,"admin":false,"hastitle":false,"navigate":true,"auto":false,"size":{"rows":15,"cols":15},"grid":["B","O","O","E","D",".","E","L","S","A",".","R","A","F","A","M","A","T","E","Y",".","V","O","O","M",".","A","M","E","X","W","H","O","L","E","B","E","A","N","C","O","F","F","E","E","S","U","E",".","V","E","N","M","O",".","H","T","M","L",".",".",".",".","W","A","L","K",".","F","A","Y","E",".",".",".","C","A","R","E","T","O","E","L","A","B","O","R","A","T","E","L","E","A","D",".","W","E","E",".","S","U","S","S","E","X","I","I","I",".",".",".","L","I","L",".",".",".","A","N","I","N","O","S","T","R","A",".","C","O","P",".","I","D","O","L","G","U","E","R","I","L","L","A","W","A","R","F","A","R","E",".",".",".","O","S","L","O",".","P","I","E","S",".",".",".",".","T","R","U","E",".","L","W","O","R","D",".","U","S","E","T","H","E","P","R","I","C","E","I","S","R","I","G","H","T","S","A","N","E",".","D","A","R","N",".","U","R","G","E","S","K","I","T","S",".","S","T","E","T",".","M","E","S","S","Y"],"gridnums":[1,2,3,4,5,0,6,7,8,9,0,10,11,12,13,14,0,0,0,0,0,15,0,0,0,0,16,0,0,0,17,0,0,0,0,18,0,0,0,0,19,0,0,0,0,20,0,0,0,21,0,0,0,0,0,22,0,0,0,0,0,0,0,23,0,0,0,0,24,25,0,0,0,0,0,26,27,28,0,0,0,0,29,0,0,0,0,30,31,32,33,0,0,0,0,34,0,0,0,35,0,0,0,0,0,36,0,0,0,0,0,37,0,38,0,0,0,39,0,0,40,0,0,41,42,43,0,44,0,45,0,46,0,0,0,47,0,0,0,0,0,48,0,0,0,49,0,0,0,0,0,0,0,50,0,0,0,0,51,0,0,0,0,0,0,0,52,53,0,0,0,54,55,0,0,0,0,56,57,58,59,0,0,0,0,60,0,0,0,0,0,61,0,0,0,62,0,0,0,0,63,0,0,0,0,64,0,0,0,0,65,0,0,0,0,66,0,0,0,0,67,0,0,0,0],"circles":[0,0,0,0,0,0,0,0,0,0,0,0,0,0,0,0,0,0,0,0,0,0,0,0,0,0,0,0,0,0,0,0,0,0,0,0,0,0,0,0,0,0,1,1,1,0,0,0,0,0,0,0,0,0,0,0,0,0,0,0,0,0,0,0,0,0,0,0,0,0,0,0,0,0,0,0,0,0,0,0,0,0,0,0,0,0,1,1,1,1,0,0,0,0,0,0,0,0,0,0,0,0,0,0,0,0,0,0,0,0,0,0,0,0,0,0,0,0,0,0,0,0,0,0,0,0,0,0,0,0,0,0,0,0,0,0,0,0,0,0,0,0,0,0,0,0,1,1,1,1,0,0,0,0,0,0,0,0,0,0,0,0,0,0,0,0,0,0,0,0,0,0,0,0,0,0,0,0,0,0,0,0,0,0,0,0,0,0,0,0,0,0,0,0,0,0,0,0,0,0,0,0,0,0,0,0,0,0,0,0,0,0,0,0,0,0,0,0,0,0,0,0,0,0,0],"acrossmap":null,"downmap":null,"rbars":null,"bbars":null,"clues":{"across":["1. Expressed displeasure, as for an opposing team","6. &quot;Frozen&quot; queen","10. Tennis&#39;s Nadal, informally","14. To whom you might cry &quot;Ahoy!&quot;","15. &quot;Va-va-___!&quot;","16. What&#39;s missing in ___erican ___press","17. Input for a barista&#39;s grinder","20. Take to court","21. Payment app whose name is now a verb","22. Web designer&#39;s code","23. What baseball players, striking employees and pet dogs each do","24. Actress Dunaway","26. &quot;Can you say more about that?&quot;","33. Starring role","34. Tiny","35. Duke of ___, title for Prince Harry","36. Three on a grandfather clock","37. &quot;___ Abner&quot;","39. The difference between Mara and Maria?","40. Cosa ____ (Mafia)","44. Police officer","46. False god","47. Tactic employed by the Vietcong","50. Capital of Norway","51. Desserts with crusts","52. T, on a test","54. Love, with &quot;the&quot;","56. &quot;___ as directed&quot; (medicine bottle caution)","59. Classic game show … or a hint to 17-, 26- and 47-Across","62. Compos mentis","63. &quot;Shoot!&quot;","64. Implores","65. First-aid boxes, e.g.","66. Leave in, editorially","67. Like a kindergarten room, often"],"down":["1. German luxury cars","2. Honolulu&#39;s island","3. Great Plains tribe","4. Reef predator","5. Textile factory container","6. Balanced disposition","7. Rich soil","8. &quot;Why, you little ...&quot;","9. &quot;The Walking Dead&quot; cable channel","10. Ceiling beams","11. Radio frequency letters","12. Have empathy (for)","13. Lumberjack&#39;s tool","18. Underneath","19. &quot;Silly goose!&quot;","23. Middle column on a calendar: Abbr.","25. Situps tighten them","26. Hold tightly (to)","27. Vowel quintet","28. Uptick in salary","29. Classic German camera","30. Carne ___ (taco choice)","31. Choir member","32. Banish, as from a country","38. Rock bottom","41. Word that would seem to be a portmanteau of &quot;traveling groups,&quot; but isn&#39;t","42. Early ___ (morning person)","43. The complete set","45. Twosomes","46. Hypotheticals","48. Feline meme since around 2006","49. &quot;The Shining&quot; plot device that became significant when read backward","52. Cuisine with pad see ew","53. High cost in New York and San Francisco","55. &quot;Now, where ___ we?&quot;","56. Popular fleece-lined boots","57. The Rolling Stones&#39; &quot;___ a Rainbow&quot;","58. Online crafts marketplace","59. [For shame!]","60. Things checked by T.S.A. workers","61. Anger"]},"answers":{"across":["BOOED","ELSA","RAFA","MATEY","VOOM","AMEX","WHOLEBEANCOFFEE","SUE","VENMO","HTML","WALK","FAYE","CARETOELABORATE","LEAD","WEE","SUSSEX","III","LIL","ANI","NOSTRA","COP","IDOL","GUERILLAWARFARE","OSLO","PIES","TRUE","LWORD","USE","THEPRICEISRIGHT","SANE","DARN","URGES","KITS","STET","MESSY"],"down":["BMWS","OAHU","OTOE","EEL","DYEVAT","EVENKEEL","LOAM","SONOFA","AMC","RAFTERS","AMFM","FEEL","AXE","BELOW","OHYOU","WED","ABS","CLING","AEIOU","RAISE","LEICA","ASADA","TENOR","EXILE","LOWPOINT","TROUPES","RISER","ALL","PAIRS","IFS","LOLCAT","REDRUM","THAI","RENT","WERE","UGGS","SHES","ETSY","TSK","IDS","IRE"]}}