{"title":"READY, SET ... GETS LOW!","author":"Nancy Stark and Will Nediger","editor":"Will Shortz","copyright":"2020, The New York Times","publisher":"The New York Times","date":"3/15/2020","notepad":null,"jnotes":"<p>The inversion story about <em>Le Bateau</em> (42-Down) was the subject of <a href=\"https://www.xwordinfo.com/Crossword?date=11/23/2008\">this 2008 crossword</a> by David J. Kahn. I wrote about it on <a href=\"https://wordplay.blogs.nytimes.com/2008/11/22/art/?rref=XWordInfo\">Wordplay</a>.</p>\r\n\r\n<p><a href=\"https://www.imdb.com/title/tt7363336/\"><em>Tea With the Dames</em></a> (60-Across) is charming. The other Dames besides <a href=\"https://www.imdb.com/name/nm0001132/\">Judi DENCH</a> are <a href=\"https://www.imdb.com/name/nm0040586/\">Eileen Atkins</a>, <a href=\"https://www.imdb.com/name/nm0687506/\">Joan Plowright</a>, and <a href=\"https://www.imdb.com/name/nm0001749/\">Maggie Smith</a>. You can watch it on Amazon Video.</p>","shadecircles":null,"interpretcolors":null,"key":null,"hold":null,"track":null,"autowrap":null,"mini":null,"id":null,"id2":null,"code":null,"dow":"Sunday","type":null,"target":"/Crossword?date=3/15/2020","valid":true,"uniclue":false,"admin":false,"hastitle":true,"navigate":true,"auto":false,"size":{"rows":21,"cols":21},"grid":["A","B","B","A",".","I","C","U",".","S","C","A","D","S",".","A","P","C","A","L","C","D","E","E","D",".","F","O","P",".","O","A","K","E","N",".","H","O","O","R","A","H","A","L","L","H","A","I","L","H","A","L","L","A","L","E",".","A","R","M","A","N","I","G","L","I","D","E",".","L","I","B","E","L",".","G","A","G",".","K","A","N","Y","E","E","Y","E",".","I","T","A","L","O",".",".","R","A","K","E","D",".",".","C","A","F",".",".",".","B","O","O","B","L","U","R","R","E","D","B","L","U","E","B","I","R","D","D","E","P","A","U","L",".",".","T","E","A","P","O","Y",".","B","R","A","N","D","O","I","M","A","N",".","I","C","E",".","I","M","O",".",".","E","L","I","T","I","S","M","S","O","N","E","R","V","O","U","S","N","O","S","E","R","V","I","C","E",".",".",".","U","T","E",".","D","E","N","C","H",".","N","E","M","E","A","N",".","A","X","E","S","S","E","R","R","A",".","C","H","A","N",".","D","E","N","S",".","H","U","E","V","O","E","S","A","U",".","W","A","R","R","E","D",".","N","O","I","R","E",".","D","E","W",".",".",".","S","T","E","V","E","D","O","R","E","D","I","V","A","S","T","O","R","E","S","A","L","T","I","N","E",".",".","P","A","T",".","R","E","D",".","O","U","S","T","A","G","E","I","S","T",".","A","G","E","N","T","S",".",".","I","D","O","T","O","O","D","U","T","C","H","T","O","W","N","T","O","U","C","H","D","O","W","N",".",".",".","T","I","M",".",".","O","R","E","O","S",".",".","R","A","I","S","E",".","S","P","F","A","L","E","U","T",".","R","E","C",".","S","T","O","N","Y",".","E","M","C","E","E","L","E","T","T","E","R",".","B","C","H","O","R","D","K","E","Y","B","O","A","R","D","E","R","R","A","T","A",".","I","H","O","P","E",".","I","R","E",".","O","N","C","E","S","A","Y","H","E","Y",".","T","I","P","S","Y",".","E","S","P",".","S","T","Y","X"],"gridnums":[1,2,3,4,0,5,6,7,0,8,9,10,11,12,0,13,14,15,16,17,18,19,0,0,0,0,20,0,0,0,21,0,0,0,0,0,22,0,0,0,0,0,23,0,0,0,24,0,0,0,25,0,0,0,0,0,0,26,0,0,0,0,0,27,0,0,0,0,0,28,0,0,0,0,0,29,0,30,0,31,0,0,0,0,32,0,0,0,33,34,0,0,0,0,0,35,0,0,0,36,0,0,37,0,0,0,0,0,38,0,0,0,0,0,39,40,0,0,0,0,0,41,42,0,0,0,43,44,45,0,0,0,0,0,46,0,0,0,0,0,0,47,0,0,0,0,0,48,0,0,0,0,49,50,51,0,52,0,0,0,0,53,0,0,0,0,0,0,54,0,0,0,55,0,0,0,56,0,0,0,57,58,0,0,0,0,0,0,0,59,0,0,0,60,0,0,0,0,0,61,0,0,0,0,0,0,62,63,64,65,66,0,0,67,0,0,68,0,0,69,0,70,0,0,0,0,71,0,0,0,0,72,0,0,0,0,73,0,0,0,0,74,0,75,0,0,76,0,0,77,0,0,0,0,0,78,79,0,0,0,0,0,0,80,0,0,0,0,0,81,0,0,0,82,83,84,0,0,0,0,0,0,85,0,0,0,86,0,0,0,87,0,0,0,88,0,0,0,0,0,0,89,90,0,0,0,91,0,0,92,93,0,0,0,0,94,0,0,0,0,0,95,0,0,0,0,0,0,96,97,0,0,0,0,0,0,98,0,0,0,0,99,0,0,0,0,0,0,100,0,0,0,0,0,101,102,103,104,0,0,105,106,0,107,0,0,0,108,109,0,0,0,0,110,111,0,0,0,112,0,0,0,0,113,0,114,0,115,0,0,0,0,0,116,0,0,0,0,0,117,0,0,0,0,0,0,118,0,0,0,0,0,119,0,0,0,120,0,0,0,121,0,0,0,0,0,0,122,0,0,0,0,0,123,0,0,0,124,0,0,0],"circles":null,"acrossmap":null,"downmap":null,"rbars":null,"bbars":null,"clues":{"across":["1. Palindromic band with the palindromic song title &quot;SOS&quot;","5. Place for an oxygen tent, for short","8. A whole bunch","13. High-level H.S. math class","19. Exploit","20. Dandy","21. Like many barrels","22. &quot;Yay!&quot;","23. Cheer for beer on campus?","26. Milan-based fashion brand","27. Skate effortlessly","28. Put down in print","29. Part of a strip","31. West of Chicago","32. Discerning judgment","33. Author Calvino","35. Played the fall guy?","37. Half-___ (rhyming order)","38. Hoot at an out-of-focus nature photograph?","43. Chicago university","46. Small three-legged table","47. Two-time Best Actor, 1954 and 1972","48. &quot;___ Old Cowhand&quot; (Bing Crosby hit)","49. Put away","52. &quot;If you ask me,&quot; briefly","53. Something populists revile","54. Antsy feeling when one is out of cellphone range?","59. Sport ___","60. One of the dames in 2018&#39;s &quot;Tea With the Dames&quot;","61. Like the lion slain by Hercules","62. Cans","66. &quot;Tilted Arc&quot; sculptor Richard","68. Jackie on the Hollywood Walk of Fame","70. Places to sleep","71. Spanish omelet ingredient","72. Isaac&#39;s firstborn","73. Fought","75. Bête ___","77. Counterpart of frost","78. Where a demanding dockworker gets supplies?","82. Snack item with a salient anagram?","85. Word that&#39;s its own synonym in reverse","86. Symbol of danger or anger","87. Boot","88. Discriminating against elders","89. They&#39;ve got talent","92. &quot;Ditto!&quot;","94. Landing in Rotterdam?","98. Curry or Rice","99. Snack items with their name on the top and bottom","100. Result of union negotiations, often","101. Lotion bottle abbr.","104. Native seal hunter","107. Part of a college application, informally","108. Unfeeling","110. Roaster or toaster","112. It&#39;s not legal","114. Piano that plays only a certain three notes?","117. Slips","118. &quot;Fingers crossed!&quot;","119. Wrath","120. A long time ago","121. Willie Mays phrase","122. A little tight","123. Pseudoscientific subj.","124. Charon&#39;s river"],"down":["1. &quot;Waste not, want not,&quot; e.g.","2. It has a button in the middle","3. Show to be untrue","4. Reason that some students struggle in school, for short","5. &quot;___ were you ...&quot;","6. Joint effort, slangily","7. Requiring difficult pedaling, say","8. Exclusive","9. Phone","10. Pseudonymously","11. Manny&#39;s last name on &quot;Modern Family&quot;","12. Slip through","13. &quot;Of course!&quot;","14. Bill padding","15. Time out?","16. Stuffed and deep-fried rice balls, in Italian cuisine","17. Name tag holders","18. Political system with a paramount leader","24. Vocal quintet?","25. More or less","30. Work well together","34. Translation of the French &quot;vivre&quot; or German &quot;leben&quot;","35. Rested","36. World capital settled by Vikings circa the ninth century","38. Scourge","39. Apt rhyme for &quot;constrain&quot;","40. Martin Sheen&#39;s real first name","41. Name of seven Danish kings","42. &quot;Le ___,&quot; Matisse work that hung upside down at the Museum of Modern Art for 47 days","43. Neglect","44. Acts dramatically","45. Bakery/cafe chain","50. Like a bowl","51. Cheat, informally","53. Refusing to answer directly","55. Suggested intake level, for short","56. Glass fragment","57. Correct","58. &quot;Two Sisters&quot; or &quot;Two Young Girls at the Piano&quot;","63. Struck","64. Exceedingly","65. Site of a 1976 South African uprising","67. Quaintly countrified","69. Virtual animals in an early 2000s fad","71. &quot;___ Got the Whole World in His Hands&quot;","73. Attended","74. Alternative to a snake","76. They catch waves","79. Nickname on &quot;The Addams Family&quot;","80. Shakespeare&#39;s &quot;You, too?&quot;","81. Bugs Bunny, e.g.","82. Sob stories","83. Christina of pop","84. &quot;Here, move over&quot;","89. Not much at all","90. Trattoria dumplings","91. New England fish","93. Dork","95. &quot;Catch-22&quot; pilot","96. Cloth that may get a lot of tears","97. Handy types","101. Meager","102. Walker ___, 1962 National Book Award winner","103. Shipping option","105. Sundance state","106. Place for un béret","108. Concessions","109. It beats a deuce","111. Stock sounds","113. Bit of sun","115. Short flight","116. Informal affirmative"]},"answers":{"across":["ABBA","ICU","SCADS","APCALC","DEED","FOP","OAKEN","HOORAH","ALLHAILHALLALE","ARMANI","GLIDE","LIBEL","GAG","KANYE","EYE","ITALO","RAKED","CAF","BOOBLURREDBLUEBIRD","DEPAUL","TEAPOY","BRANDO","IMAN","ICE","IMO","ELITISM","SONERVOUSNOSERVICE","UTE","DENCH","NEMEAN","AXES","SERRA","CHAN","DENS","HUEVO","ESAU","WARRED","NOIRE","DEW","STEVEDOREDIVASTORE","SALTINE","PAT","RED","OUST","AGEIST","AGENTS","IDOTOO","DUTCHTOWNTOUCHDOWN","TIM","OREOS","RAISE","SPF","ALEUT","REC","STONY","EMCEE","LETTER","BCHORDKEYBOARD","ERRATA","IHOPE","IRE","ONCE","SAYHEY","TIPSY","ESP","STYX"],"down":["ADAGE","BELLY","BELIE","ADHD","IFI","COLLAB","UPHILL","SOLE","CALL","AKA","DELGADO","SNEAKBY","AHA","PORK","COMA","ARANCINI","LANYARDS","CHIEFDOM","AEIOU","ABOUT","GEL","TOLIVE","REPOSED","DUBLIN","BANE","REIN","RAMON","ERIC","BATEAU","DISUSE","EMOTES","PANERA","CONCAVE","EUCHRE","EVASIVE","RDA","SHARD","EMEND","RENOIR","XEDOUT","EVERSO","SOWETO","RUSTIC","NEOPETS","HES","WENTTO","DRANO","RADIOS","TISH","ETTU","TOON","SADTALES","AGUILERA","LETMETRY","AWEEBIT","GNOCCHI","SCROD","DWEEB","ORR","HANKIE","DIYERS","SCANT","PERCY","FEDEX","UTAH","TETE","SOPS","TREY","MOOS","RAY","HOP","YEP"]}}