{
  "valid": true,
  "title": "New York Times, Saturday, September 28, 2024",
  "date": "9/28/2024",
  "author": "Margaret Seikel",
  "editor": "Joel Fagliano",
  "publisher": "The New York Times",
  "copyright": "2024, The New York Times",
  "notepad": null,
  "jnotes": "<p>I happen to be unreasonably fond of highland cattle.</p>\r\n\r\n<p>Euler&#39;s formula <strong>F + V &minus; E = 2</strong> notes that, for any polyhedron, the number of <strong>Faces</strong> plus the number of <strong>Vertices</strong> (corner points) minus the number of <strong>Edges</strong> will always be <strong>2</strong>. <a href=\"https://www.mathsisfun.com/geometry/eulers-formula.html\">Some examples</a>.</p>\r\n\r\n<p>Not to be confused with that other Euler&#39;s Formula that sometimes shows up in crosswords: <em>e</em><sup><em><strong>i</strong> </em>&pi;</sup> + 1 = 0.</p>",
  "key": null,
  "track": null,
  "autowrap": null,
  "mini": null,
  "id": null,
  "id2": null,
  "code": null,
  "dow": "Saturday",
  "type": null,
  "target": "/Crossword?date=9/28/2024",
  "hastitle": false,
  "navigate": true,
  "hold": false,
  "auto": false,
  "uniclue": false,
  "interpretcolors": false,
  "shadecircles": false,
  "admin": false,
  "json": true,
  "size": {
    "rows": 15,
    "cols": 15
  },
  "grid": [
    "A",
    "G",
    "A",
    "T",
    "H",
    "A",
    ".",
    ".",
    ".",
    "R",
    "E",
    "C",
    "A",
    "S",
    "T",
    "F",
    "U",
    "N",
    "R",
    "U",
    "N",
    "S",
    ".",
    ".",
    "E",
    "X",
    "A",
    "C",
    "T",
    "O",
    "T",
    "E",
    "C",
    "U",
    "M",
    "S",
    "E",
    "H",
    ".",
    "A",
    "O",
    "R",
    "T",
    "A",
    "E",
    "A",
    "S",
    "H",
    "E",
    ".",
    "W",
    "E",
    "I",
    "R",
    "D",
    ".",
    "I",
    "N",
    "N",
    "S",
    ".",
    "T",
    "O",
    "T",
    ".",
    "E",
    "D",
    "G",
    "E",
    "S",
    ".",
    "B",
    "O",
    "T",
    "H",
    ".",
    ".",
    ".",
    "H",
    "O",
    "R",
    "C",
    "H",
    "A",
    "T",
    "A",
    ".",
    "R",
    "H",
    "O",
    ".",
    "B",
    "L",
    "A",
    "U",
    ".",
    "A",
    "L",
    "C",
    "O",
    "A",
    ".",
    "M",
    "O",
    "E",
    "P",
    "E",
    "E",
    "T",
    "S",
    ".",
    "P",
    "A",
    "T",
    ".",
    "R",
    "O",
    "A",
    "N",
    "S",
    "L",
    "E",
    "T",
    ".",
    "T",
    "R",
    "I",
    "N",
    "I",
    ".",
    "O",
    "N",
    "L",
    "Y",
    ".",
    "U",
    "P",
    "S",
    ".",
    "S",
    "I",
    "T",
    "D",
    "O",
    "W",
    "N",
    "S",
    ".",
    ".",
    ".",
    "M",
    "O",
    "D",
    "E",
    ".",
    "B",
    "A",
    "C",
    "N",
    "E",
    ".",
    "C",
    "B",
    "S",
    ".",
    "B",
    "L",
    "A",
    "B",
    ".",
    "B",
    "L",
    "O",
    "G",
    "S",
    ".",
    "R",
    "U",
    "M",
    "P",
    "E",
    "L",
    "N",
    "I",
    "N",
    "O",
    ".",
    "W",
    "I",
    "S",
    "T",
    "E",
    "R",
    "I",
    "A",
    "R",
    "E",
    "C",
    "K",
    "O",
    "N",
    ".",
    ".",
    "F",
    "O",
    "R",
    "E",
    "S",
    "T",
    "S",
    "S",
    "N",
    "E",
    "E",
    "R",
    "S",
    ".",
    ".",
    ".",
    "N",
    "I",
    "N",
    "T",
    "H",
    "S"
  ],
  "gridnums": [
    1,
    2,
    3,
    4,
    5,
    6,
    0,
    0,
    0,
    7,
    8,
    9,
    10,
    11,
    12,
    13,
    0,
    0,
    0,
    0,
    0,
    14,
    0,
    0,
    15,
    0,
    0,
    0,
    0,
    0,
    16,
    0,
    0,
    0,
    0,
    0,
    0,
    17,
    0,
    18,
    0,
    0,
    0,
    0,
    0,
    19,
    0,
    0,
    0,
    0,
    20,
    0,
    0,
    21,
    0,
    0,
    22,
    0,
    0,
    0,
    0,
    23,
    0,
    0,
    0,
    24,
    0,
    0,
    0,
    0,
    0,
    25,
    0,
    0,
    0,
    0,
    0,
    0,
    26,
    27,
    0,
    0,
    0,
    0,
    0,
    28,
    0,
    29,
    0,
    0,
    0,
    30,
    31,
    0,
    0,
    0,
    32,
    0,
    0,
    0,
    0,
    0,
    33,
    0,
    0,
    34,
    0,
    0,
    0,
    0,
    0,
    35,
    0,
    0,
    0,
    36,
    37,
    0,
    0,
    0,
    38,
    0,
    0,
    0,
    39,
    40,
    0,
    0,
    0,
    0,
    41,
    0,
    0,
    0,
    0,
    42,
    0,
    0,
    0,
    43,
    0,
    0,
    0,
    0,
    44,
    0,
    0,
    0,
    0,
    0,
    45,
    0,
    0,
    46,
    0,
    47,
    0,
    0,
    0,
    0,
    0,
    48,
    49,
    50,
    0,
    51,
    0,
    0,
    0,
    0,
    52,
    0,
    0,
    0,
    0,
    0,
    53,
    0,
    0,
    54,
    55,
    0,
    0,
    0,
    56,
    0,
    0,
    57,
    0,
    0,
    58,
    0,
    0,
    0,
    0,
    59,
    0,
    0,
    0,
    0,
    0,
    0,
    0,
    60,
    0,
    0,
    0,
    0,
    0,
    0,
    61,
    0,
    0,
    0,
    0,
    0,
    0,
    0,
    0,
    62,
    0,
    0,
    0,
    0,
    0
  ],
  "circles": null,
  "acrossmap": null,
  "downmap": null,
  "rbars": null,
  "bbars": null,
  "clues": {
    "across": [
      "1. First name in mysteries",
      "7. Like a Broadway revival, often",
      "13. Noncompetitive races",
      "15. &quot;Precisely!,&quot; informally",
      "16. Military leader who helped capture Detroit in 1812",
      "18. Vital carriers",
      "19. Author of &quot;A Hard Road to Glory: A History of the African-American Athlete&quot;",
      "20. Out of the ordinary",
      "22. Rustic respites",
      "23. Sticky-fingered sort?",
      "24. Variable in Euler&#39;s polyhedron formula (V − E + F = 2)",
      "25. This and that",
      "26. Drink made with rice milk and cinnamon",
      "29. Sigma Gamma ___ (historically Black sorority)",
      "30. Like the Danube, to Germans",
      "32. Manufacturing giant originally known as the Pittsburgh Reduction Company",
      "33. Tucker who played drums for the Velvet Underground",
      "34. Bay Area-based coffee roaster",
      "35. Pancake topper",
      "36. Speckled steeds",
      "38. Diminutive suffix",
      "39. Lopez of &quot;The Dirty Dozen&quot;",
      "41. And no more",
      "42. Boom times",
      "43. Some in-person interviews",
      "45. Dark ___",
      "47. Breakout portmanteau",
      "48. &quot;I Love Lucy&quot; airer",
      "51. Spill the beans",
      "52. Poster sites?",
      "53. Behind",
      "55. Current influencer",
      "57. Flower in Japanese heraldry",
      "59. Estimate",
      "60. Silviculture is the science of maintaining them",
      "61. Expresses contempt",
      "62. .1111, .2222, .3333, etc."
    ],
    "down": [
      "1. Shaving brand",
      "2. Anonymous online handle, at times",
      "3. Dried poblano chili",
      "4. &quot;Amen!&quot;",
      "5. Keep one&#39;s mouth shut, but not stay silent",
      "6. Pick up",
      "7. Entertains before bed, perhaps",
      "8. Skeletal prefix",
      "9. Suriname native",
      "10. Play it cool",
      "11. Intercessor for the frequently forgetful",
      "12. Gear meant to simulate barefoot running",
      "14. Angel&#39;s contribution",
      "17. Shaggy Scottish grazer",
      "21. Animated response?",
      "27. Bounces",
      "28. First name for the third second-in-command",
      "30. Supplement purporting to combat seasonal allergies",
      "31. Directive to get down",
      "34. Their work might be draining",
      "37. How some Hollywood relationships start",
      "40. Long strips of carrot or zucchini",
      "44. Brand of vegetable oil",
      "46. Many a DoorDasher&#39;s transport",
      "49. Pop",
      "50. One of the Seven Sisters",
      "54. Drive around",
      "56. Winningest country in Winter Olympic history: Abbr.",
      "58. Arm muscle, informally"
    ]
  },
  "answers": {
    "across": [
      "AGATHA",
      "RECAST",
      "FUNRUNS",
      "EXACTO",
      "TECUMSEH",
      "AORTAE",
      "ASHE",
      "WEIRD",
      "INNS",
      "TOT",
      "EDGES",
      "BOTH",
      "HORCHATA",
      "RHO",
      "BLAU",
      "ALCOA",
      "MOE",
      "PEETS",
      "PAT",
      "ROANS",
      "LET",
      "TRINI",
      "ONLY",
      "UPS",
      "SITDOWNS",
      "MODE",
      "BACNE",
      "CBS",
      "BLAB",
      "BLOGS",
      "RUMP",
      "ELNINO",
      "WISTERIA",
      "RECKON",
      "FORESTS",
      "SNEERS",
      "NINTHS"
    ],
    "down": [
      "AFTA",
      "GUEST",
      "ANCHO",
      "TRUETHAT",
      "HUM",
      "ANSWER",
      "READSTO",
      "EXO",
      "CARIB",
      "ACTNORMAL",
      "STANTHONY",
      "TOESHOES",
      "SEEDCAPITAL",
      "HIGHLANDCOW",
      "REACTIONGIF",
      "OUSTS",
      "AARON",
      "BEEPOLLEN",
      "LETSDANCE",
      "PLUMBERS",
      "ONSCREEN",
      "RIBBONS",
      "WESSON",
      "EBIKE",
      "BURST",
      "SMITH",
      "PASS",
      "NOR",
      "TRI"
    ]
  }
}