{"title":"NY Times, Tue, May 28, 2019","author":"Aimee Lucido","editor":"Will Shortz","copyright":"2019, The New York Times","publisher":"The New York Times","date":"5/28/2019","notepad":null,"jnotes":null,"shadecircles":null,"interpretcolors":null,"key":null,"hold":null,"track":null,"autowrap":null,"mini":null,"id":null,"id2":null,"code":null,"dow":"Tuesday","type":null,"target":"/Crossword?date=5/28/2019","valid":true,"uniclue":false,"admin":false,"hastitle":false,"navigate":true,"auto":false,"size":{"rows":15,"cols":15},"grid":["A","R","D","E","N",".","P","M","S",".","S","T","R","U","T","L","E","A","V","E",".","R","A","E",".","H","E","A","T","H","B","U","M","A","R","O","U","N","D",".","A","L","T","E","R","U","S","N",".","D","U","N","G","E","O","N",".","E","R","E","M","E","R","E",".","R","E","A","R","W","I","N","D","O","W",".",".","I","A","M","S",".",".",".","E","A","U",".",".",".","A","N","G","S","T",".","P","A","W","N",".","T","I","N","S","B","E","H","I","N","D","T","H","E","S","C","E","N","E","S","E","T","T","E",".","R","A","I","D",".","E","L","T","O","N",".",".",".","S","P","A",".",".",".","D","O","L","E",".",".","B","O","T","T","O","M","L","I","N","E",".","A","R","A","L","E","N","E",".","R","A","I","N","O","U","T",".","F","D","A","A","S","S","E","T",".","B","U","T","T","H","E","A","D","S","D","E","L","L","A",".","R","I","M",".","U","N","C","L","E","S","T","A","L","L",".","A","T","E",".","S","T","E","E","R"],"gridnums":[1,2,3,4,5,0,6,7,8,0,9,10,11,12,13,14,0,0,0,0,0,15,0,0,0,16,0,0,0,0,17,0,0,0,0,18,0,0,0,0,19,0,0,0,0,20,0,0,0,21,0,0,0,0,22,0,0,23,0,0,24,0,0,25,0,26,0,0,0,0,0,27,0,0,0,0,0,28,0,29,0,0,0,0,30,0,0,0,0,0,31,32,0,0,0,0,33,34,35,0,0,36,37,38,39,40,0,0,0,0,41,0,0,0,0,42,0,0,0,0,43,0,0,0,0,44,0,0,0,0,45,0,0,0,0,0,0,0,46,47,0,0,0,0,48,0,0,0,0,0,49,50,51,0,0,0,52,53,54,0,0,55,0,56,57,58,0,0,0,59,0,0,0,0,0,60,0,61,0,0,62,0,0,63,0,0,64,0,0,0,0,65,0,0,0,66,0,0,0,0,0,67,0,0,0,68,0,0,0,0,69,0,0,0,0,0,70,0,0,0,71,0,0,0,0],"circles":null,"acrossmap":null,"downmap":null,"rbars":null,"bbars":null,"clues":{"across":["1. Elizabeth of cosmetics","6. Residents of London&#39;s 10 Downing St.","9. Walk proudly","14. &quot;Go now!&quot;","15. Singer Carly ___ Jepsen","16. ___ bar (toffee candy)","17. Wander locally with no plans","19. Change","20. Blue Angels&#39; org.","21. Basement of a castle, perhaps","23. Before, to bards","24. Little more than","26. Hitchcock movie with James Stewart and Grace Kelly","28. Purina alternative","30. Water under le pont","31. Unsettled feeling","33. &quot;___ Stars&quot; (long-running show in which experts appraise and buy antiques)","36. Tuna holders","40. Backstage","43. Suffix with bachelor or kitchen","44. Visit at 2 a.m., say, as a fridge","45. John who&#39;s the subject of 2019&#39;s &quot;Rocketman&quot;","46. Place to get pampered","48. Food company with a sunburst in its logo","49. Final amount","55. Asia&#39;s ___ Sea","58. Opposite of WSW","59. Weather-related game cancellation","61. Rx watchdog","62. It&#39;s a good thing","64. Disagree ... or a hint to the starts of 17-, 26-, 40- and 49-Across","66. Street in &quot;Perry Mason&quot;","67. Basket part grabbed after slam-dunking","68. Prince Harry, to Prince George and Princess Charlotte","69. Suddenly stop, as an engine","70. Downed, as a sandwich","71. Have the wheel"],"down":["1. Photo display option","2. Find a second function for","3. &quot;Hell, yeah!&quot;","4. Work done while tethered to a space station, for short","5. Superbrainy sort","6. Dried plum","7. Japanese comic art","8. Passover meal","9. Twain who sang &quot;Man! I Feel Like a Woman!&quot;","10. ___ Aviv","11. Assigned stars to","12. In ___ (unborn)","13. Intentionally lost","18. Not just mine","22. Jesse of the 1936 Olympics","25. Like bunny slopes, among all ski runs","27. Chocolaty spread","29. Everest, e.g.: Abbr.","31. Honest ___","32. Final amount","33. Group whose activities pick up in Sept.","34. Tuna type","35. When U.S. election results are usually published: Abbr.","37. Communicate (with)","38. Prefix with liberal","39. I.R.S. digits: Abbr.","41. Emmy genre","42. Co. leader","47. Website&#39;s access page","48. Book after Num.","49. Alternative to a door between rooms","50. Beginning","51. Nikola who invented the induction motor","52. Cooperative, balanced type, they say","53. Arctic people","54. Response to &quot;Who broke this?!&quot;","56. Confuse","57. Intense beam","60. Ergo","63. Right angle","65. Tonsillitis-treating doc"]},"answers":{"across":["ARDEN","PMS","STRUT","LEAVE","RAE","HEATH","BUMAROUND","ALTER","USN","DUNGEON","ERE","MERE","REARWINDOW","IAMS","EAU","ANGST","PAWN","TINS","BEHINDTHESCENES","ETTE","RAID","ELTON","SPA","DOLE","BOTTOMLINE","ARAL","ENE","RAINOUT","FDA","ASSET","BUTTHEADS","DELLA","RIM","UNCLE","STALL","ATE","STEER"],"down":["ALBUM","REUSE","DAMNRIGHT","EVA","NERD","PRUNE","MANGA","SEDER","SHANIA","TEL","RATED","UTERO","THREW","OURS","OWENS","EASIEST","NUTELLA","MTN","ABE","NET","PTA","AHI","WED","INTERFACE","NEO","SSN","DRAMA","CEO","PORTAL","DEUT","BEADS","ONSET","TESLA","LIBRA","INUIT","NOTME","ADDLE","LASER","THUS","ELL","ENT"]}}