{"title":"NY Times, Fri, Oct 29, 2021","author":"Aimee Lucido","editor":"Will Shortz","copyright":"2021, The New York Times","publisher":"The New York Times","date":"10/29/2021","notepad":null,"jnotes":null,"shadecircles":null,"interpretcolors":null,"key":null,"hold":null,"track":null,"autowrap":null,"mini":null,"id":null,"id2":null,"code":null,"dow":"Friday","type":null,"target":"/Crossword?date=10/29/2021","valid":true,"uniclue":false,"admin":false,"hastitle":false,"navigate":true,"auto":false,"size":{"rows":15,"cols":15},"grid":["C","H","O","C","O","T","A","C","O",".","B","A","S","E","S","H","E","L","L","T","O","P","A","Y",".","A","L","E","X","A","U","N","D","E","R","W","I","R","E",".","D","I","P","P","Y","C","D","T",".","O","N","E","G",".","S","A","S","H","E","S","K","R","I","S",".","S","C","A","R","Y","S","T","O","R","Y","L","I","M","O","S",".","E","M","I","R","S",".","R","T","E","E","X","E","M","P","T",".","E","A","U",".","S","A","S","S",".",".",".","M","A","I","L",".","L","P","G","A",".",".",".","M","D","S","E",".","T","A","B",".","S","O","N","I","C","S","E","R","N",".","C","H","I","R","P",".","A","S","N","A","P","D","O","U","B","L","E","D","A","R","E",".","A","F","R","O","I","N","G","O","O","D",".","V","E","N","A",".","R","O","N","A","E","G","I","S",".","H","U","M","O","N","G","O","U","S","N","O","I","S","E",".","I","R","E","C","K","O","N","S","O","S","N","E","E","R",".","M","A","D","H","A","T","T","E","R"],"gridnums":[1,2,3,4,5,6,7,8,9,0,10,11,12,13,14,15,0,0,0,0,0,0,0,0,0,16,0,0,0,0,17,0,0,0,0,0,0,0,0,0,18,0,0,0,0,19,0,0,0,20,0,0,0,0,21,0,0,0,0,0,22,0,0,23,0,24,0,0,25,0,0,0,0,0,0,26,0,0,0,27,0,28,0,0,0,0,0,29,0,0,30,0,0,0,0,31,0,32,0,0,0,33,0,0,0,0,0,0,34,0,0,35,0,36,0,37,0,0,0,0,38,39,40,0,0,41,0,42,0,43,0,0,44,45,46,47,0,0,0,48,0,0,0,49,0,50,0,0,0,0,51,0,0,52,0,0,0,0,0,53,0,54,0,0,0,55,0,0,0,0,0,0,56,0,0,57,0,58,0,0,59,0,0,0,0,0,60,0,0,0,0,61,0,0,0,62,0,0,0,0,0,63,0,0,0,0,0,0,0,0,64,0,0,0,0,0,65,0,0,0,0,0,0,0,0],"circles":null,"acrossmap":null,"downmap":null,"rbars":null,"bbars":null,"clues":{"across":["1. Rhyming ice cream treat","10. They may be loaded or covered","15. What there will be if you cross the wrong person","16. If you ask her to make you a sandwich, she&#39;ll say &quot;OK, you&#39;re a sandwich&quot;","17. Boob tube?","18. Foolish in an endearing way","19. Summer setting in the Windy City","20. Ten C-notes","21. Bachelorette party accessories","22. One in the Jenner family","24. One might begin &quot;It was a dark and stormy night ...&quot;","26. High rollers&#39; rollers","28. Some world leaders","29. Way to go: Abbr.","30. Absolved","32. French word that sounds like a letter of the alphabet","33. Ask &quot;Why should I?,&quot; say","34. Vote by ___","36. Org. involving course work","38. Dept. store stock","41. Neighbor of Caps Lock","43. N.B.A. team coached in the &#39;70s by Bill Russell","47. Sea eagle","48. [More worms, mama!]","50. Easy-peasy","51. Nickelodeon&#39;s longest-running game show","54. Hairstyle for 2-Down","55. Tight (with)","56. Certain blood vessel, to a physician","58. ___ Burgundy, Will Ferrell persona","59. Shield adorned with Medusa&#39;s head","60. Ginormous","62. Static, e.g.","63. &quot;That sounds &#39;bout right&quot;","64. Twisted look","65. Lewis Carroll character who asks &quot;Does your watch tell you what year it is?&quot;"],"down":["1. Response between a smile and a belly laugh","2. Woodstock headliner","3. Bygone","4. The Browns, on scoreboards","5. Oaxacan &quot;other&quot;","6. Burgs","7. Individually","8. I Spy or Backseat Bingo","9. Spanish &quot;Hey!&quot;","10. Fierce","11. Most desirable, as guests","12. Ulta competitor","13. Whizzes","14. Accepts a ring, perhaps","21. Ice cream shop supplies","23. River in Picardy","25. Yemeni money","27. Facial spot","31. Gave faithfully, in a way","33. ___ Stark, role for which Sophie Turner was Emmy-nominated","35. Put down","37. ___ step further","38. Traffic dividers","39. Talk long and boringly","40. Wearable blanket","42. Virtuosa&#39;s display","44. Short person&#39;s group photo position, ideally","45. Go barhopping, say","46. Name on many a sports jersey","48. Dealmaking pro","49. Taking a heavy science course load, perhaps","52. Capital near the old Oregon Trail","53. Eldest son of Cain","57. &quot;Puppy Love&quot; singer, 1960","60. He/___ pronouns","61. Caught"]},"answers":{"across":["CHOCOTACO","BASES","HELLTOPAY","ALEXA","UNDERWIRE","DIPPY","CDT","ONEG","SASHES","KRIS","SCARYSTORY","LIMOS","EMIRS","RTE","EXEMPT","EAU","SASS","MAIL","LPGA","MDSE","TAB","SONICS","ERN","CHIRP","ASNAP","DOUBLEDARE","AFRO","INGOOD","VENA","RON","AEGIS","HUMONGOUS","NOISE","IRECKONSO","SNEER","MADHATTER"],"down":["CHUCKLE","HENDRIX","OLDTIME","CLE","OTRO","TOWNS","APIECE","CARGAME","OYE","BADASS","ALIST","SEPHORA","EXPERTS","SAYSYES","SYRUPS","SOMME","RIAL","SPA","TITHED","SANSA","LAID","GOA","MEDIANS","DRONEON","SNUGGIE","BRAVURA","INFRONT","CAROUSE","SPONSOR","CLOSER","PREMED","BOISE","ENOCH","ANKA","HIM","GOT"]}}